eclyptic/__init__.py
eclyptic/eclyptic.py
eclyptic-1.2.0.dist-info/licenses/LICENSE
eclyptic-1.2.0.dist-info/METADATA
eclyptic-1.2.0.dist-info/WHEEL
eclyptic-1.2.0.dist-info/top_level.txt
eclyptic-1.2.0.dist-info/RECORD
