Metadata-Version: 2.4
Name: eclyptic
Version: 1.2.0
Summary: Eclyptic Asymmetric Encryption: Minimal ECIES-style encryption with elliptic curves.
Author-email: JT Steinbach <jacob@jts.gg>
License: Proprietary Use-Only License
Project-URL: Homepage, https://jts.gg/eclyptic
Project-URL: Repository, https://github.com/jtsteinbach/eclyptic
Requires-Python: >=3.8
License-File: LICENSE
Requires-Dist: cryptography<43,>=42.0.5
Dynamic: license-file
